.coveragerc
.flake8
.gitignore
MANIFEST.in
README.md
benchmark.py
pytest.ini
setup.py
.github/workflows/python-package.yml
.vscode/settings.json
pintless/__init__.py
pintless/default_units.json
pintless/errors.py
pintless/pytypes.py
pintless/quantity.py
pintless/registry.py
pintless/unit.py
pintless.egg-info/PKG-INFO
pintless.egg-info/SOURCES.txt
pintless.egg-info/dependency_links.txt
pintless.egg-info/requires.txt
pintless.egg-info/top_level.txt
tests/test_quantity.py
tests/test_registry.py
tests/test_unit.py